odoo/addons/purchase_analytic_global/README.rst
odoo/addons/purchase_analytic_global/__init__.py
odoo/addons/purchase_analytic_global/__manifest__.py
odoo/addons/purchase_analytic_global/i18n/es.po
odoo/addons/purchase_analytic_global/i18n/fr.po
odoo/addons/purchase_analytic_global/i18n/it.po
odoo/addons/purchase_analytic_global/i18n/nl.po
odoo/addons/purchase_analytic_global/i18n/pt_BR.po
odoo/addons/purchase_analytic_global/i18n/purchase_analytic_global.pot
odoo/addons/purchase_analytic_global/models/__init__.py
odoo/addons/purchase_analytic_global/models/purchase_order.py
odoo/addons/purchase_analytic_global/readme/CONTRIBUTORS.md
odoo/addons/purchase_analytic_global/readme/CREDITS.md
odoo/addons/purchase_analytic_global/readme/DESCRIPTION.md
odoo/addons/purchase_analytic_global/static/description/icon.png
odoo/addons/purchase_analytic_global/static/description/index.html
odoo/addons/purchase_analytic_global/tests/__init__.py
odoo/addons/purchase_analytic_global/tests/test_purchase_analytic_global.py
odoo/addons/purchase_analytic_global/views/purchase_order.xml
odoo_addon_purchase_analytic_global-18.0.1.0.0.7.dist-info/METADATA
odoo_addon_purchase_analytic_global-18.0.1.0.0.7.dist-info/WHEEL
odoo_addon_purchase_analytic_global-18.0.1.0.0.7.dist-info/top_level.txt
odoo_addon_purchase_analytic_global-18.0.1.0.0.7.dist-info/RECORD
